seanalgorithms3/__init__.py
seanalgorithms3/readfile.py
seanalgorithms3/arrays/DynamicArray.py
seanalgorithms3/arrays/__init__.py
seanalgorithms3/arrays/add_to_array_form.py
seanalgorithms3/arrays/array_partition.py
seanalgorithms3/arrays/assign_cookies.py
seanalgorithms3/arrays/best_time_to_buy_stock.py
seanalgorithms3/arrays/best_time_to_buy_stock_all.py
seanalgorithms3/arrays/candies_people.py
seanalgorithms3/arrays/coins_in_a_line.py
seanalgorithms3/arrays/contains_duplicate_one.py
seanalgorithms3/arrays/contains_duplicate_range.py
seanalgorithms3/arrays/degree_array.py
seanalgorithms3/arrays/distribute_candies.py
seanalgorithms3/arrays/duplicate_zeroes.py
seanalgorithms3/arrays/find_all_dissapeared_numbers.py
seanalgorithms3/arrays/find_all_duplicates.py
seanalgorithms3/arrays/find_pivot_index.py
seanalgorithms3/arrays/find_pivot_index_v2.py
seanalgorithms3/arrays/find_set_mismatch.py
seanalgorithms3/arrays/first_missing_positive.py
seanalgorithms3/arrays/friends_of_ages.py
seanalgorithms3/arrays/increasing_triplets.py
seanalgorithms3/arrays/intersect_two_array.py
seanalgorithms3/arrays/intersect_two_array_v2.py
seanalgorithms3/arrays/is_monotonic.py
seanalgorithms3/arrays/k_diff_pairs.py
seanalgorithms3/arrays/largest_number_twice_of_others.py
seanalgorithms3/arrays/longest_continuous_increasing_subsequence.py
seanalgorithms3/arrays/majority_element_2.py
seanalgorithms3/arrays/max_average_subarray.py
seanalgorithms3/arrays/max_consecutive_ones.py
seanalgorithms3/arrays/max_product_three_numbers.py
seanalgorithms3/arrays/maximize_distance_to_nearest_person.py
seanalgorithms3/arrays/maximum_subarray.py
seanalgorithms3/arrays/merge_intervals.py
seanalgorithms3/arrays/merge_sorted_array.py
seanalgorithms3/arrays/min_moves_to_equal_elements.py
seanalgorithms3/arrays/minimum_moves_to_equal_array.py
seanalgorithms3/arrays/move_zeroes.py
seanalgorithms3/arrays/my_calendar_two.py
seanalgorithms3/arrays/next_greater_element.py
seanalgorithms3-0.5.dist-info/LICENSE
seanalgorithms3-0.5.dist-info/METADATA
seanalgorithms3-0.5.dist-info/WHEEL
seanalgorithms3-0.5.dist-info/top_level.txt
seanalgorithms3-0.5.dist-info/RECORD
