Metadata-Version: 2.1
Name: seanalgorithms3
Version: 0.5
Summary: Python algorithms3
Home-page: https://github.com/seanlab3/algorithms3
Author: seanlab
Author-email: seanlabcoding33@gmail.com
License: UNKNOWN
Platform: UNKNOWN
Classifier: License :: OSI Approved :: MIT License
License-File: LICENSE
Requires-Dist: cython
